styled_print/__init__.py
styled_print/core.py
styled_print-0.1.3.dist-info/LICENSE
styled_print-0.1.3.dist-info/METADATA
styled_print-0.1.3.dist-info/WHEEL
styled_print-0.1.3.dist-info/top_level.txt
styled_print-0.1.3.dist-info/RECORD
