Metadata-Version: 2.1
Name: styled_print
Version: 0.1.3
Summary: A flexible terminal text styling utility for color, background, and custom formatting options.
Home-page: https://github.com/webbro-software/styled_print
Author: Usmonov Shoxruxmirzo
Author-email: usmonovshohruxmirzo@gmail.com
Classifier: Programming Language :: Python :: 3
Classifier: License :: OSI Approved :: MIT License
Classifier: Operating System :: OS Independent
Requires-Python: >=3.6
License-File: LICENSE
Requires-Dist: termcolor
